pyTokenizer/__init__.py
pyTokenizer-1.1.4.dist-info/LICENSE.md
pyTokenizer-1.1.4.dist-info/METADATA
pyTokenizer-1.1.4.dist-info/WHEEL
pyTokenizer-1.1.4.dist-info/top_level.txt
pyTokenizer-1.1.4.dist-info/RECORD
